{"id":"ad90517c-31f7-49a4-a4e7-7e997f4ce5b3","script":"Project Summary The AI-Powered Educational Content Transformation Platform is a comprehensive project plan to create a world-class application that transforms educational content into engaging, personalized learning experiences through multiple modalities. Key Features and Insights 1. Core Transformation Features: The platform will offer advanced features such as smart video processing, podcast generation, document processing, and AI learning assistant capabilities. 2. Technical Architecture: The project uses a microservices architecture with Python as the primary language, React for frontend development, and AWS as the primary cloud service provider. 3. Development Roadmap: The plan is divided into four phases: Foundation (Weeks 1-4), Core Features (Weeks 5-12), Advanced Features (Weeks 13-20), and Polish and Scale (Weeks 21-26). 4. Monetization Strategy: The platform will offer four pricing tiers, including a free tier, as well as additional revenue streams through API access for developers and white-label solutions. 5. Success Metrics: The project aims to achieve technical KPIs such as processing accuracy and platform uptime, as well as business KPIs like monthly active users and monthly recurring revenue. Key Takeaways Focus on delivering value quickly, gathering user feedback, and maintaining code quality and user experience. * The platform has the potential to revolutionize how people learn by providing engaging, personalized learning experiences.","voice":"default_en","speed":1,"backgroundMusic":false,"musicType":"none","analysis":{"wordCount":1687,"sentenceCount":40,"paragraphCount":1,"characterCount":14373,"readingTime":7,"complexity":"complex","contentType":"technical","contentHash":"c17761493323521ced280b5fc685be1e","estimatedTokens":4791,"metadata":{"avgWordsPerSentence":42.18,"avgSentencesPerParagraph":40}},"audio":{"audioId":"chatterbox_en_3914f696","audioUrl":"/audio/chatterbox_en_3914f696.wav","duration":85.8,"fileSize":4118478,"model":"Chatterbox-Multilingual-Advanced"},"createdAt":"2025-09-11T20:38:21.736Z"}
